Workbook
Name _Div1: #REF!
Name _Div1: #REF!
Name _Div2: #REF!
Name _Div2: #REF!
Name _Div3: #REF!
Name _Div3: #REF!
Name _Div4: #REF!
Name _Div4: #REF!
Name _Regression_Int: 1
Name coup: [1]Convexity!$C$7
Name g_firm: #REF!
Name g_firm: #REF!
Name g_firm: #REF!
Name IQ_CH: 110000
Name IQ_CQ: 5000
Name IQ_CY: 10000
Name IQ_DAILY: 500000
Name IQ_FH: 100000
Name IQ_FQ: 500
Name IQ_FY: 1000
Name IQ_LTM: 2000
Name IQ_MONTH: 15000
Name IQ_NTM: 6000
Name IQ_WEEK: 50000
Name IQ_YTD: 3000
Name k: #REF!
Name k: #REF!
Name k: #REF!
Name k_eq: #REF!
Name k_eq: #REF!
Name mat: [1]Convexity!$C$9
Name price: [1]Convexity!$C$10
Name Price4: #REF!
Name Price4: #REF!
Name Price4: #REF!
Name Print_Area_MI: #REF!
Name Print_Area_MI: #REF!
Name rdebt: #REF!
Name rdebt: #REF!
Name Selling_Price: '[2]Base Case'!$B$11
Name tax_rate: #REF!
Name tax_rate: #REF!
Name tax_rate: #REF!
Name taxtable: #REF!
Name taxtable: #REF!
Name taxtable: #REF!
Name taxtable: #REF!
Name taxtable: #REF!
Name term_g: #REF!
Name term_g: #REF!
Name Variable_Cost_per_unit: '[2]Base Case'!$B$12
Name WACC_5: #REF!
Name WACC_5: #REF!
Name WACC_5: #REF!
Name ytm: [1]Convexity!$C$8

Sheet Capital Allocation
B2: Capital Allocation. Optimal Captial Allocation using Maixum Utility
B3: Capital Allocation > Asset Classes Allocation > Security Selection
B5: Risky Pf (P) only
B6: rf: rate of return of risk-free asset | D6: 0.04
B7: E(Rp): expected return of risky pf | D7: ='Asset Classes Allocation'!D26 -> 0.27487674
B8: 𝜎 p: SD of risky pf | D8: ='Asset Classes Allocation'!E26 -> 0.3365847
L9: 0.4 | M9: 0.1339507 | N9: 0.13463388 | O9: 0.088634995 | P9: =$F$21+1/2*$D$17*N9^2 -> 0.13401148
B10: Complete Pf (C). Risk free + Risky Pf
B11: y: weight of risky pf | D11: =(D7-D6)/(D17*D8^2) -> 0.41464963
B12: 1-y: weight of risk free asset | D12: =1-D11 -> 0.58535037
B13: E(rc): expected return of the Complete pf | D13: =D11*D7+D12*D6 -> 0.13739156
B14: 𝜎 c: SD of Complete pf | D14: =D11*D8 -> 0.13956472
B15: Slope: Capital Allocation Line ( Sharpe) | D15: =(D7-D6)/D8 -> 0.6978236
B16: Risk Tolerance Score | D16: 75
B17: Risk Aversion Index (A: 1~20)* | D17: =20*(1-D16/100) -> 5
B18: Utility at the risk aversion level | D18: =D13-1/2*D17*D14^2 -> 0.088695778
B19: *Bear (1~5), Normal (1~10), Bull (1~20), Bubble (1~30)
F21: =D18 -> 0.088695778
B22: W of risky pf: y | C22: E(rc) on CAL | D22: 𝜎 c | E22: Utiliity | F22: E(rc) on Indiff.
B23: Max. U | C23: =D13 -> 0.13739156 | D23: =D14 -> 0.13956472 | E23: =D18 -> 0.088695778 | F23: =$F$21+1/2*$D$17*D23^2 -> 0.13739156
B24: 0.1 | C24: 0.063487674 | D24: 0.03365847 | E24: 0.060655443 | F24: =$F$21+1/2*$D$17*D24^2 -> 0.09152801
B25: 0.2 | C25: 0.086975349 | D25: 0.067316939 | E25: 0.075646423 | F25: =$F$21+1/2*$D$17*D25^2 -> 0.1000247
B26: 0.3 | C26: 0.11046302 | D26: 0.10097541 | E26: 0.084972941 | F26: =$F$21+1/2*$D$17*D26^2 -> 0.11418586
B27: 0.4 | C27: 0.1339507 | D27: 0.13463388 | E27: 0.088634995 | F27: =$F$21+1/2*$D$17*D27^2 -> 0.13401148
B28: 0.5 | C28: 0.15743837 | D28: 0.16829235 | E28: 0.086632587 | F28: =$F$21+1/2*$D$17*D28^2 -> 0.15950156
B29: 0.6 | C29: 0.18092605 | D29: 0.20195082 | E29: 0.078965716 | F29: =$F$21+1/2*$D$17*D29^2 -> 0.19065611
B30: 0.7 | C30: 0.20441372 | D30: 0.23560929 | E30: 0.065634381 | F30: =$F$21+1/2*$D$17*D30^2 -> 0.22747512
B31: 0.8 | C31: 0.2279014 | D31: 0.26926776 | E31: 0.046638585 | F31: =$F$21+1/2*$D$17*D31^2 -> 0.26995859
B32: 0.9 | C32: 0.25138907 | D32: 0.30292623 | E32: 0.021978325 | F32: =$F$21+1/2*$D$17*D32^2 -> 0.31810652
B33: 1 | C33: 0.27487674 | D33: 0.3365847 | E33: -0.0083463979 | F33: =$F$21+1/2*$D$17*D33^2 -> 0.37191892

Sheet Asset Classes Allocation
B2: Asset Classes Allocation Analysis: Optimal Complete Pf Model
B3: Capital Allocation > Asset Classes Allocation > Security Selection
B5: Securities | C5: Expected Return | D5: Standard Deviation | E5: Corr. Coefficient B,E | F5: Covariance B,E | H5: Efficient Frontier meets CAL with Optimal Risky Pf
B6: Bond Pf (B) | C6: ='Data. Securities'!E7+'Data. Securities'!L7 -> -0.1153439 | D6: ='Data. Securities'!L8 -> 0.15055577 | E6: =CORREL('Data. Securities'!AF39:AF97,'Data. Securities'!AI39:AI97) -> 0.4991574 | F6: =$D$6*$D$7*$E$6 -> 0.025294685
B7: Equity Pf (E) | C7: ='Security Allocation'!C56+C8 -> 0.27487674 | D7: ='Security Allocation'!C57 -> 0.3365847
B8: T-Bill | C8: ='Capital Allocation'!D6 -> 0.04 | D8: 0
B10: Risky Asset Portfolio: Weights | F10: Reward to Variability
B11: Bond weight | C11: Equity weight | D11: Expected Return | E11: Standard Deviation | F11: (Sharpe ratio)
B12: 1 | C12: 0 | D12: =$C$6*$B12+$C$7*$C12 -> -0.1153439 | E12: =($B12^2*$D$6^2+$C12^2*$D$7^2+2*$B12*$C12*$F$6)^0.5 -> 0.15055577 | F12: =(D12-$C$8)/E12 -> -1.031803
B13: 0.9 | C13: 0.1 | D13: =$C$6*$B13+$C$7*$C13 -> -0.076321832 | E13: =($B13^2*$D$6^2+$C13^2*$D$7^2+2*$B13*$C13*$F$6)^0.5 -> 0.1550685 | F13: =(D13-$C$8)/E13 -> -0.75013194
B14: 0.8 | C14: 0.2 | D14: =$C$6*$B14+$C$7*$C14 -> -0.037299768 | E14: =($B14^2*$D$6^2+$C14^2*$D$7^2+2*$B14*$C14*$F$6)^0.5 -> 0.16472029 | F14: =(D14-$C$8)/E14 -> -0.46927896
B15: 0.7 | C15: 0.3 | D15: =$C$6*$B15+$C$7*$C15 -> 0.0017222963 | E15: =($B15^2*$D$6^2+$C15^2*$D$7^2+2*$B15*$C15*$F$6)^0.5 -> 0.1786803 | F15: =(D15-$C$8)/E15 -> -0.21422453
B16: 0.6 | C16: 0.4 | D16: =$C$6*$B16+$C$7*$C16 -> 0.04074436 | E16: =($B16^2*$D$6^2+$C16^2*$D$7^2+2*$B16*$C16*$F$6)^0.5 -> 0.19603026 | F16: =(D16-$C$8)/E16 -> 0.003797171
B17: 0.5 | C17: 0.5 | D17: =$C$6*$B17+$C$7*$C17 -> 0.079766425 | E17: =($B17^2*$D$6^2+$C17^2*$D$7^2+2*$B17*$C17*$F$6)^0.5 -> 0.21595466 | F17: =(D17-$C$8)/E17 -> 0.18414247
B18: 0.4 | C18: 0.6 | D18: =$C$6*$B18+$C$7*$C18 -> 0.11878849 | E18: =($B18^2*$D$6^2+$C18^2*$D$7^2+2*$B18*$C18*$F$6)^0.5 -> 0.23780729 | F18: =(D18-$C$8)/E18 -> 0.33131233
B19: 0.3 | C19: 0.7 | D19: =$C$6*$B19+$C$7*$C19 -> 0.15781055 | E19: =($B19^2*$D$6^2+$C19^2*$D$7^2+2*$B19*$C19*$F$6)^0.5 -> 0.26110446 | F19: =(D19-$C$8)/E19 -> 0.45120085
B20: 0.2 | C20: 0.8 | D20: =$C$6*$B20+$C$7*$C20 -> 0.19683262 | E20: =($B20^2*$D$6^2+$C20^2*$D$7^2+2*$B20*$C20*$F$6)^0.5 -> 0.28549274 | F20: =(D20-$C$8)/E20 -> 0.54934012
B21: 0.1 | C21: 0.9 | D21: =$C$6*$B21+$C$7*$C21 -> 0.23585468 | E21: =($B21^2*$D$6^2+$C21^2*$D$7^2+2*$B21*$C21*$F$6)^0.5 -> 0.31071532 | F21: =(D21-$C$8)/E21 -> 0.6303348
B22: 0 | C22: 1 | D22: =$C$6*$B22+$C$7*$C22 -> 0.27487674 | E22: =($B22^2*$D$6^2+$C22^2*$D$7^2+2*$B22*$C22*$F$6)^0.5 -> 0.3365847 | F22: =(D22-$C$8)/E22 -> 0.6978236
B23: A. Minimum Variance Portfolio of Risky Assets | D23: Expected Return | E23: Min. Standard Deviation | F23: Sharpe Ratio
B24: 0.60190754 | C24: =1-$B$24 -> 0.39809246 | D24: =$C$6*$B24+$C$7*$C24 -> 0.04 | E24: =((($B$24^2)*($D$6^2))+(($C$24^2)*($D$7^2))+(2*$B$24*$C$24*$F$6))^0.5 -> 0.19567289 | F24: =(D24-$C$8)/E24 -> -2.7555095e-10 | G24: short-not allowed
B25: B. Optimal Risky Portfolio. Maximum of Sharpe ratio | D25: Expected Return | E25: Standard Deviation | F25: Max. of Sharpe Ratio
B26: 0 | C26: =1-B26 -> 1 | D26: =$C$6*$B26+$C$7*$C26 -> 0.27487674 | E26: =((($B$26^2)*($D$6^2))+(($C$26^2)*($D$7^2))+(2*$B$26*$C$26*$F$6))^0.5 -> 0.3365847 | F26: =(D26-$C$8)/E26 -> 0.6978236 | G26: short-not allowed
B28: C. Optimal Complete Portfolio with U w/ Risk-Free Asset
B29: Weight y: Optimal Risky Portfolio | D29: =(D26-C8)/('Capital Allocation'!D17*E26^2) -> 0.41464963
B30: Weight (1-y): Risk-Free Asset | D30: =1-D29 -> 0.58535037
B31: Bond weight in the Optimal Complete Pf | D31: =D29*B26 -> 0
B32: Equity weight in the Optimal Complete Pf | D32: =D29*C26 -> 0.41464963
B33: E(rc): expected return of the Overall Complete pf | D33: =D29*D26+D30*C8 -> 0.13739156
B34: 𝜎 c: SD of Overall Complete pf | D34: =D29*E26 -> 0.13956472
B35: Sharpe Ratio (Max. Slope of CAL) | D35: =(D33-C8)/D34 -> 0.6978236

Sheet Security Allocation
B2: Index Portfolio Model. SPDR + Active Portfolio (Large Growth)
B4: Panel A. Risk Parameters of Pf A (annualized) | C4: QQQ | D4: ='Data. Securities'!G6 -> V | E4: ='Data. Securities'!H6 -> MA | F4: ='Data. Securities'!I6 -> TSM | G4: ='Data. Securities'!J6 -> GOOGL | H4: ='Data. Securities'!K6 -> NVDA
B5: Beta | C5: ='Data. Securities'!F17 -> 1 | D5: ='Data. Securities'!G17 -> 0.5799856 | E5: ='Data. Securities'!H17 -> 0.63469353 | F5: ='Data. Securities'!I17 -> 1.1525127 | G5: ='Data. Securities'!J17 -> 0.91485133 | H5: ='Data. Securities'!K17 -> 1.9568273
B6: SD of Excess Return | C6: ='Data. Securities'!F8 -> 0.20793811 | D6: ='Data. Securities'!G8 -> 0.22645417 | E6: ='Data. Securities'!H8 -> 0.25197245 | F6: ='Data. Securities'!I8 -> 0.37745677 | G6: ='Data. Securities'!J8 -> 0.27133133 | H6: ='Data. Securities'!K8 -> 0.50993551
B7: SD of Residual (e), Firm specific Component | C7: ='Data. Securities'!F10 -> 0 | D7: ='Data. Securities'!G10 -> 0.19166863 | E7: ='Data. Securities'!H10 -> 0.21464434 | F7: ='Data. Securities'!I10 -> 0.39916163 | G7: ='Data. Securities'!J10 -> 0.1934743 | H7: ='Data. Securities'!K10 -> 0.30735556
B8: SD of Systematic Component | C8: =C5*$C$6 -> 0.20793811 | D8: =D5*$C$6 -> 0.12060111 | E8: =E5*$C$6 -> 0.13197697 | F8: =F5*$C$6 -> 0.23965131 | G8: =G5*$C$6 -> 0.19023246 | H8: =H5*$C$6 -> 0.40689898
B9: Correlation with the Market Index | C9: =C5*$C$6/C6 -> 1 | D9: =D5*$C$6/D6 -> 0.53256299 | E9: =E5*$C$6/E6 -> 0.52377541 | F9: =F5*$C$6/F6 -> 0.63491062 | G9: =G5*$C$6/G6 -> 0.70110758 | H9: =H5*$C$6/H6 -> 0.79794204
B11: Panel B. Correlation Matrix | C11: =C4 -> QQQ | D11: =D4 -> V | E11: =E4 -> MA | F11: =F4 -> TSM | G11: =G4 -> GOOGL | H11: =H4 -> NVDA
B12: {=TRANSPOSE(C11:H11)} -> QQQ | C12: ='Data. Securities'!P7 -> 1
B13: V | C13: ='Data. Securities'!P8 -> 0.53256299 | D13: ='Data. Securities'!Q8 -> 1
B14: MA | C14: ='Data. Securities'!P9 -> 0.52377541 | D14: ='Data. Securities'!Q9 -> 0.2789434 | E14: ='Data. Securities'!R9 -> 1
B15: TSM | C15: ='Data. Securities'!P10 -> 0.63491062 | D15: ='Data. Securities'!Q10 -> 0.33812989 | E15: ='Data. Securities'!R10 -> 0.33255057 | F15: ='Data. Securities'!S10 -> 1
B16: GOOGL | C16: ='Data. Securities'!P11 -> 0.70110758 | D16: ='Data. Securities'!Q11 -> 0.37338395 | E16: ='Data. Securities'!R11 -> 0.36722291 | F16: ='Data. Securities'!S11 -> 0.44514065 | G16: ='Data. Securities'!T11 -> 1
B17: NVDA | C17: ='Data. Securities'!P12 -> 0.79794204 | D17: ='Data. Securities'!Q12 -> 0.42495439 | E17: ='Data. Securities'!R12 -> 0.41794242 | F17: ='Data. Securities'!S12 -> 0.50662187 | G17: ='Data. Securities'!T12 -> 0.55944321 | H17: ='Data. Securities'!U12 -> 1
B19: Panel C. The Index Model Covariance Matrix | C19: =C4 -> QQQ | D19: =D4 -> V | E19: =E4 -> MA | F19: =F4 -> TSM | G19: =G4 -> GOOGL | H19: =H4 -> NVDA
B20: {=TRANSPOSE(C19:H19)} -> QQQ | C20: ='Data. Securities'!P16 -> 0.043238257
B21: V | C21: ='Data. Securities'!P17 -> 0.025077566 | D21: ='Data. Securities'!Q17 -> 0.05128149
B22: MA | C22: ='Data. Securities'!P18 -> 0.027443042 | D22: ='Data. Securities'!Q18 -> 0.015916569 | E22: ='Data. Securities'!R18 -> 0.063490114
B23: TSM | C23: ='Data. Securities'!P19 -> 0.04983264 | D23: ='Data. Securities'!Q19 -> 0.028902213 | E23: ='Data. Securities'!R19 -> 0.031628454 | F23: ='Data. Securities'!S19 -> 0.14247361
B24: GOOGL | C24: ='Data. Securities'!P20 -> 0.039556577 | D24: ='Data. Securities'!Q20 -> 0.022942245 | E24: ='Data. Securities'!R20 -> 0.025106303 | F24: ='Data. Securities'!S20 -> 0.039556577 | G24: ='Data. Securities'!T20 -> 0.073620693
B25: NVDA | C25: ='Data. Securities'!P21 -> 0.084609803 | D25: ='Data. Securities'!Q21 -> 0.049072467 | E25: ='Data. Securities'!R21 -> 0.053701295 | F25: ='Data. Securities'!S21 -> 0.097513873 | G25: ='Data. Securities'!T21 -> 0.077405391 | H25: ='Data. Securities'!U21 -> 0.26003422
B27: Panel D. Correlation of Residuals in Pf A | C27: =C19 -> QQQ | D27: =D19 -> V | E27: =E19 -> MA | F27: =F19 -> TSM | G27: =G19 -> GOOGL | H27: =H19 -> NVDA
B28: =B20 -> QQQ
B29: =B21 -> V | D29: ='Data. Securities'!Q26 -> 1
B30: =B22 -> MA | D30: ='Data. Securities'!Q27 -> 0.8942885 | E30: ='Data. Securities'!R27 -> 1
B31: =B23 -> TSM | D31: ='Data. Securities'!Q28 -> -0.39410541 | E31: ='Data. Securities'!R28 -> -0.34825931 | F31: ='Data. Securities'!S28 -> 1
B32: =B24 -> GOOGL | D32: ='Data. Securities'!Q29 -> -0.13862563 | E32: ='Data. Securities'!R29 -> -0.22212141 | F32: ='Data. Securities'!S29 -> 0.19396612 | G32: ='Data. Securities'!T29 -> 1
B33: =B25 -> NVDA | D33: ='Data. Securities'!Q30 -> -0.27614132 | E33: ='Data. Securities'!R30 -> -0.26699746 | F33: ='Data. Securities'!S30 -> 0.18240409 | G33: ='Data. Securities'!T30 -> -0.039319653 | H33: ='Data. Securities'!U30 -> 1
B35: Panel E. Macro Forecast and Alpha Forecasts | C35: =C4 -> QQQ | D35: =D4 -> V | E35: =E4 -> MA | F35: =F4 -> TSM | G35: =G4 -> GOOGL | H35: =H4 -> NVDA
B36: Adjusted Alpha in CAPM | C36: ='Data. Securities'!F14 -> 0 | D36: ='Data. Securities'!G16 -> 0.01328677 | E36: ='Data. Securities'!H16 -> 0.013810489 | F36: ='Data. Securities'!I16 -> 0.11008244 | G36: ='Data. Securities'!J16 -> 0.044009967 | H36: ='Data. Securities'!K14 -> 0.22130898
B37: Beta | C37: =C5 -> 1 | D37: =D5 -> 0.5799856 | E37: =E5 -> 0.63469353 | F37: =F5 -> 1.1525127 | G37: =G5 -> 0.91485133 | H37: =H5 -> 1.9568273
B38: Total Equity Risk Premium E(R) | C38: =C36+C37*$C$39 -> 0.071296699 | D38: =D36+D37*$C$39 -> 0.054637828 | E38: =E36+E37*$C$39 -> 0.059062042 | F38: =F36+F37*$C$39 -> 0.19225279 | G38: =G36+G37*$C$39 -> 0.10923585 | H38: =H36+H37*$C$39 -> 0.36082431
B39: Adjusted Market risk premium = | C39: ='Data. Securities'!F7*'Data. Securities'!E27/'Data. Securities'!F27 -> 0.071296699
B41: Panel F. Active Portfolio | E41: Active Pf | F41: =D35 -> V | G41: =E35 -> MA | H41: =F35 -> TSM | I41: =G35 -> GOOGL | J41: =H35 -> NVDA
B42: Residual Variance of each security | C42: s2(e) | F42: =D7^2 -> 0.036736863 | G42: =E7^2 -> 0.046072193 | H42: =F7^2 -> 0.15933001 | I42: =G7^2 -> 0.037432306 | J42: =H7^2 -> 0.094467443
B43: Initial position of each security | C43: wi(0) = ai/s2(e) | E43: =SUM(F43:K43) -> 4.8707626 | F43: =D36/F42 -> 0.36167405 | G43: =E36/G42 -> 0.29975758 | H43: =F36/H42 -> 0.69090841 | I43: =G36/I42 -> 1.1757215 | J43: =H36/J42 -> 2.342701
B44: Scaled initial position of each security | C44: wi | E44: =SUM(F44:K44) -> 1 | F44: =F43/$E$43 -> 0.074254092 | G44: =G43/$E$43 -> 0.061542227 | H44: =H43/$E$43 -> 0.1418481 | I44: =I43/$E$43 -> 0.24138346 | J44: =J43/$E$43 -> 0.48097213
B45: Squared scaled initial position of each security | C45: [wi(0)]2 | F45: =F44^2 -> 0.0055136702 | G45: =G44^2 -> 0.0037874457 | H45: =H44^2 -> 0.020120883 | I45: =I44^2 -> 0.058265972 | J45: =J44^2 -> 0.23133419
B46: Alpha of the Active Pf | C46: aA | E46: =SUMPRODUCT(D36:H36,F44:J44) -> 0.13451824
B47: Residual Variance of Active Pf | C47: s2(eA) | E47: =SUMPRODUCT(F42:K42,F45:K45) -> 0.02761749
B48: Active Pf information ratio (APIR) | C48: aA / s2(eA) | E48: =E46/E47 -> 4.8707626
B49: Index Pf information ratio (IPIR) | C49: E(RM)/s2(M) | E49: =C38/C6^2 -> 1.6489263
B50: Initial position in Active Pf (APIR/IPIR) | C50: wA(0) | E50: =E48/E49 -> 2.9538995
B51: Beta of the Active Pf | C51: bA | E51: =SUMPRODUCT(D37:I37,F44:K44) -> 1.4076179
B53: Panel G. Optimal Risky Portfolios | C53: Overall Risky Pf | D53: =C35 -> QQQ | E53: Active Pf | F53: =F41 -> V | G53: =G41 -> MA | H53: =H41 -> TSM | I53: =I41 -> GOOGL | J53: =J41 -> NVDA
B54: w*(Optimal Pf): Short not allowed | C54: 1 | D54: =C54-E54 -> 0 | E54: 1 | F54: =$E$54*F44 -> 0.074254092 | G54: =$E$54*G44 -> 0.061542227 | H54: =$E$54*H44 -> 0.1418481 | I54: =$E$54*I44 -> 0.24138346 | J54: =$E$54*J44 -> 0.48097213
B55: Beta | C55: =D55*D54+E55*E54 -> 1.4076179 | D55: =1 -> 1 | E55: =SUMPRODUCT(D37:I37,F44:K44) -> 1.4076179
B56: Risk Premium | C56: =D56*D54+E56*E54 -> 0.23487674 | D56: =C38 -> 0.071296699 | E56: =SUMPRODUCT(D38:I38,F44:K44) -> 0.23487674
B57: Standard Deviation | C57: =SQRT((D54+E54*E51)^2*D57^2+E54^2*E47) -> 0.3365847 | D57: =C6 -> 0.20793811 | E57: =SQRT(E51^2*C6^2+E47) -> 0.3365847
B58: Sharpe Ratio (S) | C58: =C56/C57 -> 0.6978236 | D58: =D56/D57 -> 0.34287462 | E58: =E56/E57 -> 0.6978236
B59: Performance Measures
B60: Treynor Measure (T) | C60: =C56/C55 -> 0.16686116 | D60: =D56/D55 -> 0.071296699 | E60: =E56/E55 -> 0.16686116
B61: Jensen Measure (a) | C61: =SUMPRODUCT($D$54*D61+$E$54*E61) -> 0.13451824 | D61: 0 | E61: =E46 -> 0.13451824
B62: Information Ratio Measure (IR) | C62: =SUMPRODUCT($D$54*D62+$E$54*E62) -> 0.48599966 | D62: 0 | E62: =(E56-D56)/E57 -> 0.48599966
B63: Overall Performance | C63: =SUMPRODUCT($D$54*D63+$E$54*E63) -> 0.23487674 | D63: =D56 -> 0.071296699 | E63: =E56 -> 0.23487674
B64: CAPM | C64: =SUMPRODUCT($D$54*D64+$E$54*E64) -> 0.15035851 | D64: =5%+$C$39*D55 -> 0.1212967 | E64: =5%+$C$39*E55 -> 0.15035851
B65: Ratio of total risk (𝜎p/𝜎m) | C65: =SUMPRODUCT($D$54*D65+$E$54*E65) -> 1.6186773 | D65: =D57/$D$57 -> 1 | E65: =E57/$D$57 -> 1.6186773
B66: CML | C66: =SUMPRODUCT($D$54*D66+$E$54*E66) -> 0.16540635 | D66: =5%+$C$39*D65 -> 0.1212967 | E66: =5%+$C$39*E65 -> 0.16540635
B67: Selectivity (%) | C67: =SUMPRODUCT($D$54*D67+$E$54*E67) -> 0.13451824 | D67: =D56+5%-D64 -> 0 | E67: =E56+5%-E64 -> 0.13451824
B68: Diversification Effect (%) | C68: =SUMPRODUCT($D$54*D68+$E$54*E68) -> -0.01504784 | D68: =D64-D66 -> 0 | E68: =E64-E66 -> -0.01504784
B69: Net Selectivity (%) | C69: =SUMPRODUCT($D$54*D69+$E$54*E69) -> 0.14956608 | D69: =D67-D68 -> 0 | E69: =E67-E68 -> 0.14956608
B70: net Risk Premium of Pf | C70: =SUMPRODUCT($D$54*D70+$E$54*E70) -> 0.10035851 | D70: =D63-D67 -> 0.071296699 | E70: =E63-E67 -> 0.10035851

Sheet Data. Securities
B2: Data. Security Index Model
B4: Panel 1. Risk & Return Parameters in the Security Index Model | N4: Panel 2. Correlation and Covariance Matrixs in the Security Index Model
B6: Estimates annualized | E6: T-bill | F6: QQQ | G6: V | H6: MA | I6: TSM | J6: GOOGL | K6: NVDA | L6: TLT | O6: Correl (via Index) | P6: =F6 -> QQQ | Q6: =G6 -> V | R6: =H6 -> MA | S6: =I6 -> TSM | T6: =J6 -> GOOGL | U6: =K6 -> NVDA
B7: Expected excess return | E7: 0.04 | F7: =AVERAGE(E39:E97)*12 -> 0.11300699 | G7: =AVERAGE(H39:H97)*12 -> 0.091737316 | H7: =AVERAGE(M39:M97)*12 -> 0.10167097 | I7: =AVERAGE(R39:R97)*12 -> 0.25163729 | J7: =AVERAGE(W39:W97)*12 -> 0.14930285 | K7: =AVERAGE(AB39:AB97)*12 -> 0.59020165 | L7: =AVERAGE(AI39:AI97)*12 -> -0.1553439 | O7: =F6 -> QQQ | P7: 1
B8: SD of Excess Return | E8: 0 | F8: =_xlfn.STDEV.S(E39:E97)*SQRT(12) -> 0.20793811 | G8: =_xlfn.STDEV.S(H39:H97)*SQRT(12) -> 0.22645417 | H8: =_xlfn.STDEV.S(M39:M97)*SQRT(12) -> 0.25197245 | I8: =_xlfn.STDEV.S(R39:R97)*SQRT(12) -> 0.37745677 | J8: =_xlfn.STDEV.S(W39:W97)*SQRT(12) -> 0.27133133 | K8: =_xlfn.STDEV.S(AB39:AB97)*SQRT(12) -> 0.50993551 | L8: =_xlfn.STDEV.S(AI39:AI97)*SQRT(12) -> 0.15055577 | O8: =Q6 -> V | P8: =G18 -> 0.53256299 | Q8: 1
B9: Sharpe Ratio | F9: =F7/F8 -> 0.54346455 | G9: =G7/G8 -> 0.40510324 | H9: =H7/H8 -> 0.40350033 | I9: =I7/I8 -> 0.66666519 | J9: =J7/J8 -> 0.55026024 | K9: =K7/K8 -> 1.1574045 | L9: =L7/L8 -> -1.031803 | O9: =R6 -> MA | P9: =H18 -> 0.52377541 | Q9: =G18*H18 -> 0.2789434 | R9: 1
B10: SD of Residuals (e) | F10: 0 | G10: =_xlfn.STDEV.S(J39:J97)*SQRT(12) -> 0.19166863 | H10: =_xlfn.STDEV.S(O39:O97)*SQRT(12) -> 0.21464434 | I10: =_xlfn.STDEV.S(T39:T97)*SQRT(12) -> 0.39916163 | J10: =_xlfn.STDEV.S(Y39:Y97)*SQRT(12) -> 0.1934743 | K10: =_xlfn.STDEV.S(AD39:AD97)*SQRT(12) -> 0.30735556 | O10: =S6 -> TSM | P10: =I18 -> 0.63491062 | Q10: =G18*I18 -> 0.33812989 | R10: =H18*I18 -> 0.33255057 | S10: 1
B11: SD of Systematic component | F11: =F8 -> 0.20793811 | G11: =_xlfn.STDEV.S(I39:I97)*SQRT(12) -> 0.12060111 | H11: =_xlfn.STDEV.S(O39:O97)*SQRT(12) -> 0.21464434 | I11: =_xlfn.STDEV.S(S39:S97)*SQRT(12) -> 0.12697842 | J11: =_xlfn.STDEV.S(X39:X97)*SQRT(12) -> 0.19023246 | K11: =_xlfn.STDEV.S(AC39:AC97)*SQRT(12) -> 0.40689898 | O11: =T6 -> GOOGL | P11: =J18 -> 0.70110758 | Q11: =G18*J18 -> 0.37338395 | R11: =H18*J18 -> 0.36722291 | S11: =I18*J18 -> 0.44514065 | T11: 1 | AU11: 0.5 | AV11: =AU11*0.5 -> 0.25 | AW11: =AV11*0.5 -> 0.125 | AX11: =AW11*0.5 -> 0.0625 | AY11: =AX11*0.5 -> 0.03125 | AZ11: =AY11*0.5 -> 0.015625 | BA11: =AZ11*0.5 -> 0.0078125 | BB11: =BA11*0.5 -> 0.00390625
B12: Covariance | F12: =F8^2 -> 0.043238257 | G12: =_xlfn.COVARIANCE.S($E$39:$E$97,H39:H97)*12 -> 0.025077566 | H12: =_xlfn.COVARIANCE.S($E$39:$E$97,M39:M97)*12 -> 0.027443042 | I12: =_xlfn.COVARIANCE.S($E$39:$E$97,R39:R97)*12 -> 0.04983264 | J12: =_xlfn.COVARIANCE.S($E$39:$E$97,W39:W97)*12 -> 0.039556577 | K12: =_xlfn.COVARIANCE.S($E$39:$E$97,AB39:AB97)*12 -> 0.084609803 | O12: =U6 -> NVDA | P12: =K18 -> 0.79794204 | Q12: =G18*K18 -> 0.42495439 | R12: =H18*K18 -> 0.41794242 | S12: =I18*K18 -> 0.50662187 | T12: =J18*K18 -> 0.55944321 | U12: 1
B13: Alpha (Non-market risk premium in the index model) | F13: 0 | G13: =INTERCEPT(H39:H97,$E$39:$E$97)*12 -> 0.02619489 | H13: =INTERCEPT(M39:M97,$E$39:$E$97)*12 -> 0.029946161 | I13: =INTERCEPT(R39:R97,$E$39:$E$97)*12 -> 0.1213953 | J13: =INTERCEPT(W39:W97,$E$39:$E$97)*12 -> 0.045918251 | K13: =INTERCEPT(AB39:AB97,$E$39:$E$97)*12 -> 0.36906648
B14: Adjusted Alpha (a x avg. Market PE / Stock PE) | F14: =F13*$E$27/E27 -> 0 | G14: =G13*$E$27/G27 -> 0.016319175 | H14: =H13*$E$27/H27 -> 0.016607607 | I14: =I13*$E$27/I27 -> 0.11652413 | J14: =J13*$E$27/J27 -> 0.050556249 | K14: =K13*$E$27/K27 -> 0.22130898
B15: Alpha in CAPM (10 yrs market premium) | F15: 0 | G15: =(G7+$E$7-(4.3%+G17*((AVERAGE('QQQ ETF Stock 10yrs Prices '!$G$3:$G$121)*12)-4.3%))) -> 0.021327393 | H15: =(H7+$E$7-(4.3%+H17*((AVERAGE('QQQ ETF Stock 10yrs Prices '!$G$3:$G$121)*12)-4.3%))) -> 0.024902511 | I15: =(I7+$E$7-(4.3%+I17*((AVERAGE('QQQ ETF Stock 10yrs Prices '!$G$3:$G$121)*12)-4.3%))) -> 0.11468432 | J15: =(J7+$E$7-(4.3%+J17*((AVERAGE('QQQ ETF Stock 10yrs Prices '!$G$3:$G$121)*12)-4.3%))) -> 0.03997252 | K15: =(K7+$E$7-(4.3%+K17*((AVERAGE('QQQ ETF Stock 10yrs Prices '!$G$3:$G$121)*12)-4.3%))) -> 0.35976569 | O15: Covariance (via Index) | P15: =P6 -> QQQ | Q15: =Q6 -> V | R15: =R6 -> MA | S15: =S6 -> TSM | T15: =T6 -> GOOGL | U15: =U6 -> NVDA
B16: Adjusted Alpha in CAPM (a x avg. Market PE / Stock PE) | F16: =F15*$E$27/F27 -> 0 | G16: =G15*$E$27/G27 -> 0.01328677 | H16: =H15*$E$27/H27 -> 0.013810489 | I16: =I15*$E$27/I27 -> 0.11008244 | J16: =J15*$E$27/J27 -> 0.044009967 | K16: =K15*$E$27/K27 -> 0.2157318 | O16: =F6 -> QQQ | P16: =F8^2 -> 0.043238257
B17: Beta | F17: 1 | G17: =SLOPE(H39:H97,$E$39:$E$97) -> 0.5799856 | H17: =SLOPE(M39:M97,$E$39:$E$97) -> 0.63469353 | I17: =SLOPE(R39:R97,$E$39:$E$97) -> 1.1525127 | J17: =SLOPE(W39:W97,$E$39:$E$97) -> 0.91485133 | K17: =SLOPE(AB39:AB97,$E$39:$E$97) -> 1.9568273 | O17: =Q15 -> V | P17: =G17*1*P16 -> 0.025077566 | Q17: =G8^2 -> 0.05128149
B18: Correlation with Index | F18: 1 | G18: =CORREL($E$39:$E$97,H$39:H$97) -> 0.53256299 | H18: =CORREL($E$39:$E$97,M$39:M$97) -> 0.52377541 | I18: =CORREL($E$39:$E$97,R$39:R$97) -> 0.63491062 | J18: =CORREL($E$39:$E$97,W$39:W$97) -> 0.70110758 | K18: =CORREL($E$39:$E$97,AB$39:AB$97) -> 0.79794204 | L18: =CORREL($E$39:$E$97,AI$39:AI$97) -> 0.56627587 | O18: =R15 -> MA | P18: =$H$17*$P$16 -> 0.027443042 | Q18: =$H$17*G17*$P$16 -> 0.015916569 | R18: =H8^2 -> 0.063490114
B19: R Squared (Market Determination) | F19: 1 | G19: =G18^2 -> 0.28362333 | H19: =H18^2 -> 0.27434068 | I19: =I18^2 -> 0.40311149 | J19: =J18^2 -> 0.49155184 | K19: =K18^2 -> 0.6367115 | O19: =S15 -> TSM | P19: =$I$17*1*$P$16 -> 0.04983264 | Q19: =$I$17*G17*$P$16 -> 0.028902213 | R19: =$I$17*H17*$P$16 -> 0.031628454 | S19: =I8^2 -> 0.14247361
B20: 1-R Squared (Firms Specific) | F20: 0 | G20: =1-G19 -> 0.71637667 | H20: =1-H19 -> 0.72565932 | I20: =1-I19 -> 0.59688851 | J20: =1-J19 -> 0.50844816 | K20: =1-K19 -> 0.3632885 | O20: =T15 -> GOOGL | P20: =$J$17*$P$16 -> 0.039556577 | Q20: =$J$17*$P$16*G17 -> 0.022942245 | R20: =$J$17*$P$16*H17 -> 0.025106303 | S20: =$J$17*$P$16 -> 0.039556577 | T20: =J8^2 -> 0.073620693
B21: Pf Style. | C21: Value / Blend / Growth | F21: Growth | G21: Growth | H21: Growth | I21: Growth | J21: Blend | K21: Growth | L21: Credit (Investment / High Yield) | O21: =U15 -> NVDA | P21: =$K$17*$P$16 -> 0.084609803 | Q21: =$K$17*$P$16*G17 -> 0.049072467 | R21: =$K$17*$P$16*H17 -> 0.053701295 | S21: =$K$17*$P$16*I17 -> 0.097513873 | T21: =$K$17*$P$16*J17 -> 0.077405391 | U21: =K8^2 -> 0.26003422
C22: Small / Medium / Large | G22: Large | H22: Large | I22: Large | J22: Large | K22: Large | L22: Duration (longer / shorter)
C23: Sector (industry) | G23: Financial Services | H23: Financial Services | I23: Tech | J23: Communication Services | K23: Tech | L23: Issuers (Corporate / Government)
C24: Themes | G24: Electronic Payments | H24: Electronic Payments | I24: Semiconductor | J24: Online search, AI | K24: AI | L24: Inflation / close-ended / sector… | O24: Correl of Residuals | P24: =P6 -> QQQ | Q24: =Q6 -> V | R24: =R6 -> MA | S24: =S6 -> TSM | T24: =T6 -> GOOGL | U24: =U6 -> NVDA
B25: Stock Info. | C25: Current Stock Price | F25: 444.1 | G25: 329.61 | H25: 517.33 | I25: 151.82 | J25: 151.16 | K25: 101.49 | O25: =F6 -> QQQ
C26: EPS (TTM) | G26: 9.92 | H26: 13.86 | I26: 7.04 | J26: 8.04 | K26: 2.94 | O26: =Q24 -> V | Q26: 1
C27: PE Ratio (TTM) | E27: 20.7 | F27: 32.81 | G27: =G25/G26 -> 33.226815 | H27: =H25/H26 -> 37.325397 | I27: =I25/I26 -> 21.565341 | J27: =J25/J26 -> 18.800995 | K27: =K25/K26 -> 34.520408 | O27: =R24 -> MA | Q27: =CORREL(J39:J97,O39:O97) -> 0.8942885 | R27: 1
C28: 1y Forward Dividend ($) | G28: 2.36 | H28: 3.04 | I28: 2.74 | J28: 0.8 | K28: 0.04 | O28: =S24 -> TSM | Q28: =CORREL(J39:J97,T39:T97) -> -0.39410541 | R28: =CORREL(O39:O97,T39:T97) -> -0.34825931 | S28: 1
C29: 1y Forward Dividend Yield (%) | G29: =G28/G25 -> 0.0071599769 | H29: =H28/H25 -> 0.0058763265 | I29: =I28/I25 -> 0.018047688 | J29: =J28/J25 -> 0.0052924054 | K29: =K28/K25 -> 0.0003941275 | O29: =T24 -> GOOGL | Q29: =CORREL(J39:J97,Y39:Y97) -> -0.13862563 | R29: =CORREL(O39:O97,Y39:Y97) -> -0.22212141 | S29: =CORREL(T39:T97,Y39:Y97) -> 0.19396612 | T29: 1
C30: 1y Target Est. (Consensus) | G30: 374.36 | H30: 613.01 | I30: 228 | J30: 205.39 | K30: 165.48 | O30: =U24 -> NVDA | Q30: =CORREL(J39:J97,AD39:AD97) -> -0.27614132 | R30: =CORREL(O39:O97,AD39:AD97) -> -0.26699746 | S30: =CORREL(T39:T97,AD39:AD97) -> 0.18240409 | T30: =CORREL(Y39:Y97,AD39:AD97) -> -0.039319653 | U30: 1
C31: 1y Target return | G31: =G30/G25-1 -> 0.13576651 | H31: =H30/H25-1 -> 0.18494965 | I31: =I30/I25-1 -> 0.50177842 | J31: =J30/J25-1 -> 0.35875893 | K31: =K30/K25-1 -> 0.63050547
B32: Active Pf Weights* (Index model) | F32: ='Security Allocation'!D54 -> 0 | G32: ='Security Allocation'!F54 -> 0.074254092 | H32: ='Security Allocation'!G54 -> 0.061542227 | I32: ='Security Allocation'!H54 -> 0.1418481 | J32: ='Security Allocation'!I54 -> 0.24138346 | K32: ='Security Allocation'!J54 -> 0.48097213
B34: Panel 3. Price information. monthly rate of return and excess returns
B36: 60 months | C36: Invesco QQQ Trust (QQQ) | F36: Visa Inc Class A (V) | K36: Mastercard Inc (MA) | P36: Taiwan Semiconductor Manufacturing (TSM) | U36: Alphabet Inc Class A (GOOGL) | Z36: NVIDIA Corporation (NVDA) | AE36: Equity Pf | AG36: iShares 20+ Year Treasury Bond ETF (TLT) | AK36: Benchmark Check
B37: Dates | C37: Prices | D37: Monthly rate | E37: Benchmark Exces return | F37: Prices | G37: Monthly rate | H37: Exces return | I37: Mkt Prem. Systematic component | J37: Residuals. Unsystematic component | K37: Prices | L37: Monthly rate | M37: Exces return | N37: Mkt Prem. Systematic component | O37: Residuals. Unsystematic component | P37: Prices | Q37: Monthly rate | R37: Exces return | S37: Mkt Prem. Systematic component | T37: Residuals. Unsystematic component | U37: Prices | V37: Monthly rate | W37: Exces return | X37: Mkt Prem. Systematic component | Y37: Residuals. Unsystematic component | Z37: Prices | AA37: Monthly rate | AB37: Exces return | AC37: Mkt Prem. Systematic component | AD37: Residuals. Unsystematic component | AE37: Adjusted Price of Equity Pf (Back data) | AF37: Active Pf Exces return (Back data) | AG37: Prices | AH37: Monthly rate | AI37: Exces return | AK37: Active Pf Excess Retun - Benchmark (Back Data)
B38: 43952 | C38: 233.24 | F38: 195.24 | K38: 300.89 | P38: 50.33 | U38: 71.68 | Z38: 8.88 | AE38: =C38 -> 233.24 | AG38: 163.59
B39: 43983 | C39: 247.47 | D39: =C39/C38-1 -> 0.061010118 | E39: =D39-$E$7/12 -> 0.057676785 | F39: 193.17 | G39: =F39/F38-1 -> -0.010602336 | H39: =G39-$E$7/12 -> -0.013935669 | I39: =$G$17*E39 -> 0.033451705 | J39: =H39-$G$13/12-I39 -> -0.049570281 | K39: 295.7 | L39: =K39/K38-1 -> -0.017248828 | M39: =L39-$E$7/12 -> -0.020582162 | N39: =$H$17*E39 -> 0.036607082 | O39: =M39-$G$13/12-N39 -> -0.059372152 | P39: 56.77 | Q39: =P39/P38-1 -> 0.12795549 | R39: =Q39-$E$7/12 -> 0.12462216 | S39: =$I$17*E39 -> 0.066473227 | T39: =R39-$I$13/12-S39 -> 0.048032659 | U39: 70.9 | V39: =U39/U38-1 -> -0.010881696 | W39: =V39-$E$7/12 -> -0.01421503 | X39: =$J$17*E39 -> 0.052765684 | Y39: =W39-$J$13/12-X39 -> -0.070807234 | Z39: 9.5 | AA39: =Z39/Z38-1 -> 0.06981982 | AB39: =AA39-$E$7/12 -> 0.066486486 | AC39: =$K$17*E39 -> 0.11286351 | AD39: =AB39-$K$13/12-AC39 -> -0.077132564 | AE39: =AE38*(1+AF39) -> 243.48456 | AF39: =$F$32*E39+$G$32*H39+$H$32*M39+$I$32*R39+$J$32*W39+$K$32*AB39 -> 0.043922838 | AG39: 163.93 | AH39: =AG39/AG38-1 -> 0.0020783666 | AI39: =AH39-$E$7/12 -> -0.0012549667 | AK39: =AF39-E39 -> -0.013753947
B40: 44013 | C40: 265.65 | D40: =C40/C39-1 -> 0.07346345 | E40: =D40-$E$7/12 -> 0.070130117 | F40: 190.4 | G40: =F40/F39-1 -> -0.014339701 | H40: =G40-$E$7/12 -> -0.017673034 | I40: =$G$17*E40 -> 0.040674458 | J40: =H40-$G$13/12-I40 -> -0.060530399 | K40: 308.53 | L40: =K40/K39-1 -> 0.043388569 | M40: =L40-$E$7/12 -> 0.040055236 | N40: =$H$17*E40 -> 0.044511131 | O40: =M40-$G$13/12-N40 -> -0.0066388027 | P40: 78.89 | Q40: =P40/P39-1 -> 0.38964242 | R40: =Q40-$E$7/12 -> 0.38630908 | S40: =$G$17*O40 -> -0.00385041 | T40: =R40-$I$13/12-S40 -> 0.38004322 | U40: 74.4 | V40: =U40/U39-1 -> 0.049365303 | W40: =V40-$E$7/12 -> 0.04603197 | X40: =$J$17*E40 -> 0.064158631 | Y40: =W40-$J$13/12-X40 -> -0.021953182 | Z40: 10.61 | AA40: =Z40/Z39-1 -> 0.11684211 | AB40: =AA40-$E$7/12 -> 0.11350877 | AC40: =$K$17*E40 -> 0.13723253 | AD40: =AB40-$K$13/12-AC40 -> -0.054479299 | AE40: =AE39*(1+AF40) -> 273.1059 | AF40: =$F$32*E40+$G$32*H40+$H$32*M40+$I$32*R40+$J$32*W40+$K$32*AB40 -> 0.12165591 | AG40: 171 | AH40: =AG40/AG39-1 -> 0.043128164 | AI40: =AH40-$E$7/12 -> 0.039794831 | AK40: =AF40-E40 -> 0.051525797
B41: 44044 | C41: 294.73 | D41: =C41/C40-1 -> 0.10946734 | E41: =D41-$E$7/12 -> 0.10613401 | F41: 211.99 | G41: =F41/F40-1 -> 0.11339286 | H41: =G41-$E$7/12 -> 0.11005952 | I41: =$G$17*E41 -> 0.061556198 | J41: =H41-$G$13/12-I41 -> 0.046320419 | K41: 358.19 | L41: =K41/K40-1 -> 0.1609568 | M41: =L41-$E$7/12 -> 0.15762346 | N41: =$H$17*E41 -> 0.06736257 | O41: =M41-$G$13/12-N41 -> 0.088077984 | P41: 79.25 | Q41: =P41/P40-1 -> 0.004563316 | R41: =Q41-$E$7/12 -> 0.0012299827 | S41: =$G$17*O41 -> 0.051083962 | T41: =R41-$I$13/12-S41 -> -0.059970254 | U41: 81.48 | V41: =U41/U40-1 -> 0.09516129 | W41: =V41-$E$7/12 -> 0.091827957 | X41: =$J$17*E41 -> 0.097096841 | Y41: =W41-$J$13/12-X41 -> -0.0090954051 | Z41: 13.37 | AA41: =Z41/Z40-1 -> 0.26013195 | AB41: =AA41-$E$7/12 -> 0.25679862 | AC41: =$K$17*E41 -> 0.20768594 | AD41: =AB41-$K$13/12-AC41 -> 0.018357142 | AE41: =AE40*(1+AF41) -> 317.82045 | AF41: =$F$32*E41+$G$32*H41+$H$32*M41+$I$32*R41+$J$32*W41+$K$32*AB41 -> 0.16372607 | AG41: 162.19 | AH41: =AG41/AG40-1 -> -0.051520468 | AI41: =AH41-$E$7/12 -> -0.054853801 | AK41: =AF41-E41 -> 0.057592055
B42: 44075 | C42: 277.69 | D42: =C42/C41-1 -> -0.057815628 | E42: =D42-$E$7/12 -> -0.061148961 | F42: 199.97 | G42: =F42/F41-1 -> -0.056700788 | H42: =G42-$E$7/12 -> -0.060034121 | I42: =$G$17*E42 -> -0.035465517 | J42: =H42-$G$13/12-I42 -> -0.026751512 | K42: 338.17 | L42: =K42/K41-1 -> -0.055892124 | M42: =L42-$E$7/12 -> -0.059225458 | N42: =$H$17*E42 -> -0.03881085 | O42: =M42-$G$13/12-N42 -> -0.022597515 | P42: 81.07 | Q42: =P42/P41-1 -> 0.0229653 | R42: =Q42-$E$7/12 -> 0.019631966 | S42: =$G$17*O42 -> -0.013106233 | T42: =R42-$I$13/12-S42 -> 0.022621925 | U42: 73.28 | V42: =U42/U41-1 -> -0.10063819 | W42: =V42-$E$7/12 -> -0.10397153 | X42: =$J$17*E42 -> -0.055942209 | Y42: =W42-$J$13/12-X42 -> -0.051855839 | Z42: 13.53 | AA42: =Z42/Z41-1 -> 0.011967091 | AB42: =AA42-$E$7/12 -> 0.0086337572 | AC42: =$K$17*E42 -> -0.11965796 | AD42: =AB42-$K$13/12-AC42 -> 0.097536177 | AE42: =AE41*(1+AF42) -> 309.47376 | AF42: =$F$32*E42+$G$32*H42+$H$32*M42+$I$32*R42+$J$32*W42+$K$32*AB42 -> -0.026262298 | AG42: 163.26 | AH42: =AG42/AG41-1 -> 0.0065972008 | AI42: =AH42-$E$7/12 -> 0.0032638675 | AK42: =AF42-E42 -> 0.034886663
B43: 44105 | C43: 269.24 | D43: =C43/C42-1 -> -0.030429616 | E43: =D43-$E$7/12 -> -0.033762949 | F43: 181.71 | G43: =F43/F42-1 -> -0.091313697 | H43: =G43-$E$7/12 -> -0.09464703 | I43: =$G$17*E43 -> -0.019582024 | J43: =H43-$G$13/12-I43 -> -0.077247914 | K43: 288.64 | L43: =K43/K42-1 -> -0.1464648 | M43: =L43-$E$7/12 -> -0.14979813 | N43: =$H$17*E43 -> -0.021429125 | O43: =M43-$G$13/12-N43 -> -0.13055191 | P43: 83.87 | Q43: =P43/P42-1 -> 0.034538054 | R43: =Q43-$E$7/12 -> 0.03120472 | S43: =$G$17*O43 -> -0.075718228 | T43: =R43-$I$13/12-S43 -> 0.096806673 | U43: 80.81 | V43: =U43/U42-1 -> 0.10275655 | W43: =V43-$E$7/12 -> 0.099423217 | X43: =$J$17*E43 -> -0.030888079 | Y43: =W43-$J$13/12-X43 -> 0.12648477 | Z43: 12.53 | AA43: =Z43/Z42-1 -> -0.07390983 | AB43: =AA43-$E$7/12 -> -0.077243163 | AC43: =$K$17*E43 -> -0.066068262 | AD43: =AB43-$K$13/12-AC43 -> -0.041930441 | AE43: =AE42*(1+AF43) -> 301.74521 | AF43: =$F$32*E43+$G$32*H43+$H$32*M43+$I$32*R43+$J$32*W43+$K$32*AB43 -> -0.024973198 | AG43: 157.57 | AH43: =AG43/AG42-1 -> -0.034852383 | AI43: =AH43-$E$7/12 -> -0.038185716 | AK43: =AF43-E43 -> 0.0087897506
B44: 44136 | C44: 299.46 | D44: =C44/C43-1 -> 0.11224187 | E44: =D44-$E$7/12 -> 0.10890853 | F44: 210.35 | G44: =F44/F43-1 -> 0.15761378 | H44: =G44-$E$7/12 -> 0.15428045 | I44: =$G$17*E44 -> 0.06316538 | J44: =H44-$G$13/12-I44 -> 0.088932159 | K44: 336.51 | L44: =K44/K43-1 -> 0.16584673 | M44: =L44-$E$7/12 -> 0.1625134 | N44: =$H$17*E44 -> 0.069123541 | O44: =M44-$G$13/12-N44 -> 0.091206948 | P44: 97.02 | Q44: =P44/P43-1 -> 0.15679027 | R44: =Q44-$E$7/12 -> 0.15345694 | S44: =$G$17*O44 -> 0.052898716 | T44: =R44-$I$13/12-S44 -> 0.090441947 | U44: 87.72 | V44: =U44/U43-1 -> 0.085509219 | W44: =V44-$E$7/12 -> 0.082175886 | X44: =$J$17*E44 -> 0.099635116 | Y44: =W44-$J$13/12-X44 -> -0.021285751 | Z44: 13.4 | AA44: =Z44/Z43-1 -> 0.06943336 | AB44: =AA44-$E$7/12 -> 0.066100027 | AC44: =$K$17*E44 -> 0.2131152 | AD44: =AB44-$K$13/12-AC44 -> -0.17777071 | AE44: =AE43*(1+AF44) -> 330.36669 | AF44: =$F$32*E44+$G$32*H44+$H$32*M44+$I$32*R44+$J$32*W44+$K$32*AB44 -> 0.094853135 | AG44: 160.02 | AH44: =AG44/AG43-1 -> 0.015548645 | AI44: =AH44-$E$7/12 -> 0.012215312 | AK44: =AF44-E44 -> -0.014055397
B45: 44166 | C45: 313.58 | D45: =C45/C44-1 -> 0.047151539 | E45: =D45-$E$7/12 -> 0.043818206 | F45: 218.73 | G45: =F45/F44-1 -> 0.039838365 | H45: =G45-$E$7/12 -> 0.036505031 | I45: =$G$17*E45 -> 0.025413928 | J45: =H45-$G$13/12-I45 -> 0.0089081955 | K45: 356.94 | L45: =K45/K44-1 -> 0.06071142 | M45: =L45-$E$7/12 -> 0.057378087 | N45: =$H$17*E45 -> 0.027811132 | O45: =M45-$G$13/12-N45 -> 0.027384047 | P45: 109.04 | Q45: =P45/P44-1 -> 0.12389198 | R45: =Q45-$E$7/12 -> 0.12055865 | S45: =$G$17*O45 -> 0.015882353 | T45: =R45-$I$13/12-S45 -> 0.09456002 | U45: 87.63 | V45: =U45/U44-1 -> -0.0010259918 | W45: =V45-$E$7/12 -> -0.0043593251 | X45: =$J$17*E45 -> 0.040087144 | Y45: =W45-$J$13/12-X45 -> -0.04827299 | Z45: 13.06 | AA45: =Z45/Z44-1 -> -0.025373134 | AB45: =AA45-$E$7/12 -> -0.028706468 | AC45: =$K$17*E45 -> 0.085744664 | AD45: =AB45-$K$13/12-AC45 -> -0.14520667 | AE45: =AE44*(1+AF45) -> 333.16937 | AF45: =$F$32*E45+$G$32*H45+$H$32*M45+$I$32*R45+$J$32*W45+$K$32*AB45 -> 0.0084835585 | AG45: 157.73 | AH45: =AG45/AG44-1 -> -0.014310711 | AI45: =AH45-$E$7/12 -> -0.017644044 | AK45: =AF45-E45 -> -0.035334648
B46: 44197 | C46: 314.39 | D46: =C46/C45-1 -> 0.0025830729 | E46: =D46-$E$7/12 -> -0.00075026043 | F46: 193.25 | G46: =F46/F45-1 -> -0.11649065 | H46: =G46-$E$7/12 -> -0.11982398 | I46: =$G$17*E46 -> -0.00043514024 | J46: =H46-$G$13/12-I46 -> -0.12157175 | K46: 316.29 | L46: =K46/K45-1 -> -0.11388469 | M46: =L46-$E$7/12 -> -0.11721802 | N46: =$H$17*E46 -> -0.00047618544 | O46: =M46-$G$13/12-N46 -> -0.11892474 | P46: 121.52 | Q46: =P46/P45-1 -> 0.11445341 | R46: =Q46-$E$7/12 -> 0.11112008 | S46: =$G$17*O46 -> -0.068974637 | T46: =R46-$I$13/12-S46 -> 0.16997844 | U46: 91.37 | V46: =U46/U45-1 -> 0.042679448 | W46: =V46-$E$7/12 -> 0.039346114 | X46: =$J$17*E46 -> -0.00068637676 | Y46: =W46-$J$13/12-X46 -> 0.03620597 | Z46: 12.99 | AA46: =Z46/Z45-1 -> -0.0053598775 | AB46: =AA46-$E$7/12 -> -0.0086932108 | AC46: =$K$17*E46 -> -0.0014681301 | AD46: =AB46-$K$13/12-AC46 -> -0.037980621 | AE46: =AE45*(1+AF46) -> 334.82429 | AF46: =$F$32*E46+$G$32*H46+$H$32*M46+$I$32*R46+$J$32*W46+$K$32*AB46 -> 0.0049672016 | AG46: 152 | AH46: =AG46/AG45-1 -> -0.036327902 | AI46: =AH46-$E$7/12 -> -0.039661235 | AK46: =AF46-E46 -> 0.0057174621
B47: 44228 | C47: 313.98 | D47: =C47/C46-1 -> -0.0013041127 | E47: =D47-$E$7/12 -> -0.0046374461 | F47: 212.39 | G47: =F47/F46-1 -> 0.099042691 | H47: =G47-$E$7/12 -> 0.095709357 | I47: =$G$17*E47 -> -0.0026896519 | J47: =H47-$G$13/12-I47 -> 0.096216102 | K47: 353.85 | L47: =K47/K46-1 -> 0.11875178 | M47: =L47-$E$7/12 -> 0.11541845 | N47: =$H$17*E47 -> -0.002943357 | O47: =M47-$G$13/12-N47 -> 0.11617889 | P47: 125.94 | Q47: =P47/P46-1 -> 0.036372614 | R47: =Q47-$E$7/12 -> 0.03303928 | S47: =$G$17*O47 -> 0.067382085 | T47: =R47-$I$13/12-S47 -> -0.04445908 | U47: 101.1 | V47: =U47/U46-1 -> 0.1064901 | W47: =V47-$E$7/12 -> 0.10315676 | X47: =$J$17*E47 -> -0.0042425737 | Y47: =W47-$J$13/12-X47 -> 0.10357281 | Z47: 13.71 | AA47: =Z47/Z46-1 -> 0.055427252 | AB47: =AA47-$E$7/12 -> 0.052093918 | AC47: =$K$17*E47 -> -0.0090746813 | AD47: =AB47-$K$13/12-AC47 -> 0.03041306 | AE47: =AE46*(1+AF47) -> 357.87779 | AF47: =$F$32*E47+$G$32*H47+$H$32*M47+$I$32*R47+$J$32*W47+$K$32*AB47 -> 0.068852537 | AG47: 143.12 | AH47: =AG47/AG46-1 -> -0.058421053 | AI47: =AH47-$E$7/12 -> -0.061754386 | AK47: =AF47-E47 -> 0.073489983
B48: 44256 | C48: 318.96 | D48: =C48/C47-1 -> 0.015860883 | E48: =D48-$E$7/12 -> 0.01252755 | F48: 211.73 | G48: =F48/F47-1 -> -0.0031074909 | H48: =G48-$E$7/12 -> -0.0064408243 | I48: =$G$17*E48 -> 0.0072657983 | J48: =H48-$G$13/12-I48 -> -0.01588953 | K48: 356.05 | L48: =K48/K47-1 -> 0.0062173237 | M48: =L48-$E$7/12 -> 0.0028839904 | N48: =$H$17*E48 -> 0.0079511546 | O48: =M48-$G$13/12-N48 -> -0.0072500717 | P48: 118.28 | Q48: =P48/P47-1 -> -0.060822614 | R48: =Q48-$E$7/12 -> -0.064155947 | S48: =$G$17*O48 -> -0.0042049372 | T48: =R48-$I$13/12-S48 -> -0.070067285 | U48: 103.13 | V48: =U48/U47-1 -> 0.02007913 | W48: =V48-$E$7/12 -> 0.016745796 | X48: =$J$17*E48 -> 0.011460845 | Y48: =W48-$J$13/12-X48 -> 0.00145843 | Z48: 13.35 | AA48: =Z48/Z47-1 -> -0.026258206 | AB48: =AA48-$E$7/12 -> -0.029591539 | AC48: =$K$17*E48 -> 0.024514252 | AD48: =AB48-$K$13/12-AC48 -> -0.084861331 | AE48: =AE47*(1+AF48) -> 350.86635 | AF48: =$F$32*E48+$G$32*H48+$H$32*M48+$I$32*R48+$J$32*W48+$K$32*AB48 -> -0.019591717 | AG48: 135.45 | AH48: =AG48/AG47-1 -> -0.053591392 | AI48: =AH48-$E$7/12 -> -0.056924725 | AK48: =AF48-E48 -> -0.032119266
B49: 44287 | C49: 337.81 | D49: =C49/C48-1 -> 0.05909832 | E49: =D49-$E$7/12 -> 0.055764986 | F49: 233.56 | G49: =F49/F48-1 -> 0.10310301 | H49: =G49-$E$7/12 -> 0.099769675 | I49: =$G$17*E49 -> 0.032342889 | J49: =H49-$G$13/12-I49 -> 0.065243879 | K49: 382.06 | L49: =K49/K48-1 -> 0.073051538 | M49: =L49-$E$7/12 -> 0.069718204 | N49: =$H$17*E49 -> 0.035393676 | O49: =M49-$G$13/12-N49 -> 0.032141621 | P49: 116.74 | Q49: =P49/P48-1 -> -0.013019953 | R49: =Q49-$E$7/12 -> -0.016353286 | S49: =$G$17*O49 -> 0.018641677 | T49: =R49-$I$13/12-S49 -> -0.045111238 | U49: 117.68 | V49: =U49/U48-1 -> 0.14108407 | W49: =V49-$E$7/12 -> 0.13775074 | X49: =$J$17*E49 -> 0.051016672 | Y49: =W49-$J$13/12-X49 -> 0.082907543 | Z49: 15.01 | AA49: =Z49/Z48-1 -> 0.12434457 | AB49: =AA49-$E$7/12 -> 0.12101124 | AC49: =$K$17*E49 -> 0.10912245 | AD49: =AB49-$K$13/12-AC49 -> -0.018866754 | AE49: =AE48*(1+AF49) -> 386.24527 | AF49: =$F$32*E49+$G$32*H49+$H$32*M49+$I$32*R49+$J$32*W49+$K$32*AB49 -> 0.10083302 | AG49: 138.64 | AH49: =AG49/AG48-1 -> 0.023551126 | AI49: =AH49-$E$7/12 -> 0.020217793 | AK49: =AF49-E49 -> 0.045068031
B50: 44317 | C50: 333.76 | D50: =C50/C49-1 -> -0.011988988 | E50: =D50-$E$7/12 -> -0.015322321 | F50: 227.3 | G50: =F50/F49-1 -> -0.026802535 | H50: =G50-$E$7/12 -> -0.030135868 | I50: =$G$17*E50 -> -0.0088867256 | J50: =H50-$G$13/12-I50 -> -0.02343205 | K50: 360.58 | L50: =K50/K49-1 -> -0.056221536 | M50: =L50-$E$7/12 -> -0.059554869 | N50: =$H$17*E50 -> -0.0097249782 | O50: =M50-$G$13/12-N50 -> -0.052012799 | P50: 117.36 | Q50: =P50/P49-1 -> 0.0053109474 | R50: =Q50-$E$7/12 -> 0.0019776141 | S50: =$G$17*O50 -> -0.030166674 | T50: =R50-$I$13/12-S50 -> 0.022028013 | U50: 117.84 | V50: =U50/U49-1 -> 0.0013596193 | W50: =V50-$E$7/12 -> -0.001973714 | X50: =$J$17*E50 -> -0.014017646 | Y50: =W50-$J$13/12-X50 -> 0.0082174111 | Z50: 16.24 | AA50: =Z50/Z49-1 -> 0.08194537 | AB50: =AA50-$E$7/12 -> 0.078612036 | AC50: =$K$17*E50 -> -0.029983137 | AD50: =AB50-$K$13/12-AC50 -> 0.077839634 | AE50: =AE49*(1+AF50) -> 398.49366 | AF50: =$F$32*E50+$G$32*H50+$H$32*M50+$I$32*R50+$J$32*W50+$K$32*AB50 -> 0.031711446 | AG50: 138.44 | AH50: =AG50/AG49-1 -> -0.0014425851 | AI50: =AH50-$E$7/12 -> -0.0047759184 | AK50: =AF50-E50 -> 0.047033768
B51: 44348 | C51: 354.24 | D51: =C51/C50-1 -> 0.061361457 | E51: =D51-$E$7/12 -> 0.058028124 | F51: 233.82 | G51: =F51/F50-1 -> 0.028684558 | H51: =G51-$E$7/12 -> 0.025351225 | I51: =$G$17*E51 -> 0.033655476 | J51: =H51-$G$13/12-I51 -> -0.010487159 | K51: 365.09 | L51: =K51/K50-1 -> 0.012507627 | M51: =L51-$E$7/12 -> 0.0091742933 | N51: =$H$17*E51 -> 0.036830075 | O51: =M51-$G$13/12-N51 -> -0.029838689 | P51: 120.16 | Q51: =P51/P50-1 -> 0.023858214 | R51: =Q51-$E$7/12 -> 0.020524881 | S51: =$G$17*O51 -> -0.01730601 | T51: =R51-$I$13/12-S51 -> 0.027714616 | U51: 122.09 | V51: =U51/U50-1 -> 0.036065852 | W51: =V51-$E$7/12 -> 0.032732519 | X51: =$J$17*E51 -> 0.053087107 | Y51: =W51-$J$13/12-X51 -> -0.024181109 | Z51: 20 | AA51: =Z51/Z50-1 -> 0.23152709 | AB51: =AA51-$E$7/12 -> 0.22819376 | AC51: =$K$17*E51 -> 0.11355102 | AD51: =AB51-$K$13/12-AC51 -> 0.0838872 | AE51: =AE50*(1+AF51) -> 447.51411 | AF51: =$F$32*E51+$G$32*H51+$H$32*M51+$I$32*R51+$J$32*W51+$K$32*AB51 -> 0.12301438 | AG51: 144.35 | AH51: =AG51/AG50-1 -> 0.042689974 | AI51: =AH51-$E$7/12 -> 0.039356641 | AK51: =AF51-E51 -> 0.064986256
... B97: 45352 | C97: 444.1 | D97: =C97/C96-1 -> -0.052930137 | E97: =D97-$E$7/12 -> -0.056263471 | F97: 329.61 | G97: =F97/F96-1 -> -0.059493237 | H97: =G97-$E$7/12 -> -0.062826571 | I97: =$G$17*E97 -> -0.032632003 | J97: =H97-$G$13/12-I97 -> -0.032377476 | K97: 517.33 | L97: =K97/K96-1 -> -0.056173831 | M97: =L97-$E$7/12 -> -0.059507164 | N97: =$H$17*E97 -> -0.035710061 | O97: =M97-$G$13/12-N97 -> -0.02598001 | P97: 151.74 | Q97: =P97/P96-1 -> -0.085903614 | R97: =Q97-$E$7/12 -> -0.089236948 | S97: =$G$17*O97 -> -0.015068032 | T97: =R97-$I$13/12-S97 -> -0.084285191 | U97: 151.16 | V97: =U97/U96-1 -> -0.02250388 | W97: =V97-$E$7/12 -> -0.025837213 | X97: =$J$17*E97 -> -0.051472711 | Y97: =W97-$J$13/12-X97 -> 0.021808977 | Z97: 101.49 | AA97: =Z97/Z96-1 -> -0.063572615 | AB97: =AA97-$E$7/12 -> -0.066905948 | AC97: =$K$17*E97 -> -0.1100979 | AD97: =AB97-$K$13/12-AC97 -> 0.01243641 | AE97: =AE96*(1+AF97) -> 1074.5272 | AF97: =$F$32*E97+$G$32*H97+$H$32*M97+$I$32*R97+$J$32*W97+$K$32*AB97 -> -0.059401997 | AG97: 87.53 | AH97: =AG97/AG96-1 -> -0.038448863 | AI97: =AH97-$E$7/12 -> -0.041782196 | AK97: =AF97-E97 -> -0.0031385261
F98: SUMMARY OUTPUT | K98: SUMMARY OUTPUT | P98: SUMMARY OUTPUT | U98: SUMMARY OUTPUT | Z98: SUMMARY OUTPUT | AK98: =AVERAGE(AK39:AK97)*12 -> 0.25566599 | AL98: Tracking Error
AK99: =_xlfn.STDEV.S(AK39:AK97) -> 0.051761856 | AL99: Standard Deviation
F100: Regression Statistics | K100: Regression Statistics | P100: Regression Statistics | U100: Regression Statistics | Z100: Regression Statistics | AK100: =CORREL(AF39:AF97,E39:E97) -> 0.87996325 | AL100: Correlation
F101: Multiple R | G101: 0.53256299 | K101: Multiple R | L101: 0.52377541 | P101: Multiple R | Q101: 0.63491062 | U101: Multiple R | V101: 0.70110758 | Z101: Multiple R | AA101: 0.79794204 | AK101: =RSQ(AF39:AF97,E39:E97) -> 0.77433531 | AL101: R^2
F102: R Square | G102: 0.28362333 | K102: R Square | L102: 0.27434068 | P102: R Square | Q102: 0.40311149 | U102: R Square | V102: 0.49155184 | Z102: R Square | AA102: 0.6367115 | AK102: =SLOPE(AF39:AF97,E39:E97) -> 1.4076179 | AL102: SLOPE
F103: Adjusted R Square | G103: 0.27105532 | K103: Adjusted R Square | L103: 0.26160982 | P103: Adjusted R Square | Q103: 0.39263976 | U103: Adjusted R Square | V103: 0.4826317 | Z103: Adjusted R Square | AA103: 0.63033801
F104: Standard Error | G104: 0.055813207 | K104: Standard Error | L104: 0.062503651 | P104: Standard Error | Q104: 0.084918003 | U104: Standard Error | V104: 0.056339013 | Z104: Standard Error | AA104: 0.089500822
F105: Observations | G105: 59 | K105: Observations | L105: 59 | P105: Observations | Q105: 59 | U105: Observations | V105: 59 | Z105: Observations | AA105: 59
F107: ANOVA | K107: ANOVA | P107: ANOVA | U107: ANOVA | Z107: ANOVA
G108: df | H108: SS | I108: MS | J108: F | L108: df | M108: SS | N108: MS | O108: F | Q108: df | R108: SS | S108: MS | T108: F | V108: df | W108: SS | X108: MS | Y108: F | AA108: df | AB108: SS | AC108: MS | AD108: F
F109: Regression | G109: 1 | H109: 0.070299031 | I109: 0.070299031 | J109: 22.567081 | K109: Regression | L109: 1 | M109: 0.084186619 | N109: 0.084186619 | O109: 21.549257 | P109: Regression | Q109: 1 | R109: 0.27759163 | S109: 0.27759163 | T109: 38.495221 | U109: Regression | V109: 1 | W109: 0.17491054 | X109: 0.17491054 | Y109: 55.105824 | Z109: Regression | AA109: 1 | AB109: 0.80023942 | AC109: 0.80023942 | AD109: 99.900093
F110: Residual | G110: 57 | H110: 0.1775615 | I110: 0.0031151141 | K110: Residual | L110: 57 | M110: 0.22268227 | N110: 0.0039067064 | P110: Residual | Q110: 57 | R110: 0.41103083 | S110: 0.0072110672 | U110: Residual | V110: 57 | W110: 0.18092281 | X110: 0.0031740844 | Z110: Residual | AA110: 57 | AB110: 0.45659264 | AC110: 0.0080103972
F111: Total | G111: 58 | H111: 0.24786053 | K111: Total | L111: 58 | M111: 0.30686888 | P111: Total | Q111: 58 | R111: 0.68862246 | U111: Total | V111: 58 | W111: 0.35583335 | Z111: Total | AA111: 58 | AB111: 1.2568321
G113: Coefficients | H113: Standard Error | I113: t Stat | J113: P-value | L113: Coefficients | M113: Standard Error | N113: t Stat | O113: P-value | Q113: Coefficients | R113: Standard Error | S113: t Stat | T113: P-value | V113: Coefficients | W113: Standard Error | X113: t Stat | Y113: P-value | AA113: Coefficients | AB113: Standard Error | AC113: t Stat | AD113: P-value
F114: Intercept | G114: 0.0021829075 | H114: 0.0073566616 | I114: 0.29672528 | J114: 0.76775483 | K114: Intercept | L114: 0.0024955134 | M114: 0.0082385198 | N114: 0.30290799 | O114: 0.76306273 | P114: Intercept | Q114: 0.010116275 | R114: 0.011192924 | S114: 0.90380979 | T114: 0.36990031 | U114: Intercept | V114: 0.0038265209 | W114: 0.0074259674 | X114: 0.51528921 | Y114: 0.6083437 | Z114: Intercept | AA114: 0.03075554 | AB114: 0.01179698 | AC114: 2.607069 | AD114: 0.011635306
F115: X Variable 1 | G115: 0.5799856 | H115: 0.12208984 | I115: 4.7504822 | J115: 1.4134472e-05 | K115: X Variable 1 | L115: 0.63469353 | M115: 0.136725 | N115: 4.6421177 | O115: 2.0707348e-05 | P115: X Variable 1 | Q115: 1.1525127 | R115: 0.18575577 | S115: 6.2044517 | T115: 6.6379544e-08 | U115: X Variable 1 | V115: 0.91485133 | W115: 0.12324002 | X115: 7.4233297 | Y115: 6.2665297e-10 | Z115: X Variable 1 | AA115: 1.9568273 | AB115: 0.19578056 | AC115: 9.9950034 | AD115: 3.8299431e-14

Sheet Data. Bond Duration & Convexity
B2: Calculate the approximate price change for a TLT using only its D* and using D* and Convexity
B4: TLT has the following characteristics:
B5: Maturity | C5: 25.72
B6: Coupon ($100 par) | C6: 0.0284
B7: Yield to maturity | C7: 0.0491
B8: Coupon (frequency) | C8: Semiannual
B9: Convexity (C) | C9: 3.42
B10: Current Bond Price | C10: =PV(C7/2,C5*2,-C6/2*100,-100) -> 69.948884 | D10: =_xlfn.FORMULATEXT(C10) -> =PV(C7/2,C5*2,-C6/2*100,-100)
B11: Modified Duration (D*) | C11: =MDURATION(DATE(2025,4,1),DATE(2051,1,1),C6,C7,2) -> 16.197545 | D11: =_xlfn.FORMULATEXT(C11) -> =MDURATION(DATE(2025,4,1),DATE(2051,1,1),C6,C7,2)
B13: Changes in YTM | C13: YTM down 100bps
B14: with D* only | C14: =-C11*-1% -> 0.16197545 | D14: =_xlfn.FORMULATEXT(C14) -> =-C11*-1%
B15: Bond Price change | C15: =C10*(1+C14) -> 81.278886 | D15: =_xlfn.FORMULATEXT(C15) -> =C10*(1+C14)
B16: with D* and Convexity | C16: =-C11*-1%+1/2*C9*-1%^2 -> 0.16214645 | D16: =_xlfn.FORMULATEXT(C16) -> =-C11*-1%+1/2*C9*-1%^2
B17: Bond Price change | C17: =C10*(1+C16) -> 81.290848 | D17: =_xlfn.FORMULATEXT(C17) -> =C10*(1+C16)

Sheet QQQ ETF Stock 10yrs Prices 
A1: Date | B1: Price | C1: Open | D1: High | E1: Low | F1: Vol. | G1: Change %
A2: 42125 | B2: 109.99 | C2: 107.99 | D2: 111.02 | E2: 105.94 | F2: 518.23M | G2: 0.0225
A3: 42156 | B3: 107.01 | C3: 110.58 | D3: 111.07 | E3: 106.58 | F3: 577.03M | G3: -0.0271
A4: 42186 | B4: 111.89 | C4: 108.07 | D4: 114.33 | E4: 105.77 | F4: 644.89M | G4: 0.0456
A5: 42217 | B5: 104.25 | C5: 111.91 | D5: 112.94 | E5: 84.7 | F5: 1.01B | G5: -0.0682
A6: 42248 | B6: 101.71 | C6: 101.66 | D6: 108.67 | E6: 98.7 | F6: 881.20M | G6: -0.0244
A7: 42278 | B7: 113.27 | C7: 101.89 | D7: 114.02 | E7: 100.43 | F7: 740.63M | G7: 0.1137
A8: 42309 | B8: 113.96 | C8: 113.57 | D8: 115.41 | E8: 109.42 | F8: 543.41M | G8: 0.0061
A9: 42339 | B9: 111.8 | C9: 114.42 | D9: 115.69 | E9: 109.32 | F9: 757.51M | G9: -0.0189
A10: 42370 | B10: 104.07 | C10: 109.37 | D10: 110.12 | E10: 97.2 | F10: 1.08B | G10: -0.0691
A11: 42401 | B11: 102.45 | C11: 103.57 | D11: 104.75 | E11: 94.79 | F11: 942.26M | G11: -0.0157
A12: 42430 | B12: 109.14 | C12: 103.4 | D12: 109.98 | E12: 103.11 | F12: 602.37M | G12: 0.0654
A13: 42461 | B13: 105.66 | C13: 108.52 | D13: 111.38 | E13: 104.82 | F13: 559.25M | G13: -0.0319
... A121: 45748 | B121: 444.1 | C121: 467.32 | D121: 479.54 | E121: 402.52 | F121: 1.02B | G121: -0.0529
